README.md
setup.py
bot_wars/__init__.py
bot_wars/get_events.py
bot_wars/get_mobs.py
bot_wars/mob_info.py
bot_wars.egg-info/PKG-INFO
bot_wars.egg-info/SOURCES.txt
bot_wars.egg-info/dependency_links.txt
bot_wars.egg-info/not-zip-safe
bot_wars.egg-info/requires.txt
bot_wars.egg-info/top_level.txt
scripts/bot_wars