Metadata-Version: 1.0
Name: bot-wars
Version: 0.2
Summary: A simple telegram bot to get mob info.
Home-page: https://github.com/kanazux/bot-wars
Author: UNKNOWN
Author-email: contato@kanazuchi.com
License: BSD2CLAUSE
Platform: UNKNOWN
